<?xml version="1.0"?>
<!DOCTYPE hibernate-mapping PUBLIC "-//Hibernate/Hibernate Mapping DTD//EN" "http://hibernate.sourceforge.net/hibernate-mapping-3.0.dtd" >
<hibernate-mapping>

    <class name="com.cinnamonbob.model.Revision" table="REVISION" lazy="false">

        <id name="id" type="java.lang.Long" column="ID" unsaved-value="0">
            <generator class="hilo"/>
        </id>
        
        <discriminator column="REVISIONTYPE" type="string" length="255"/>
        
        <property name="author" column="AUTHOR" type="string" length="255"/>
        <property name="comment" column="COMMENT" type="string" length="4096"/>
        <property name="time" column="DATE" type="long"/>
        <property name="branch" column="BRANCH" type="string" length="255"/>
        <property name="revisionString" column="REVISIONSTRING" type="string" length="255"/>

        <subclass name="com.cinnamonbob.model.NumericalRevision" discriminator-value="NUMERICAL" dynamic-update="false">
        </subclass>
        
        <subclass name="com.cinnamonbob.model.CvsRevision" discriminator-value="CVS" dynamic-update="false">
        </subclass>

    </class>

</hibernate-mapping>
